email_sender/__init__.py
email_sender/mail.py
py_send_e_mail-0.1.dist-info/LICENSE
py_send_e_mail-0.1.dist-info/METADATA
py_send_e_mail-0.1.dist-info/WHEEL
py_send_e_mail-0.1.dist-info/top_level.txt
py_send_e_mail-0.1.dist-info/RECORD
