Metadata-Version: 2.1
Name: py-send-e-mail
Version: 0.1
Summary: Easy Email sender Python package
Home-page: https://github.com/chapimenge3/Email_Sender
Author: Temkin Mengistu
Author-email: chapimenge3@gmail.com
License: UNKNOWN
Platform: UNKNOWN
Classifier: Programming Language :: Python :: 3
Classifier: License :: OSI Approved :: MIT License
Classifier: Operating System :: OS Independent
Requires-Python: >=3.6
